{"trial_id": "0125", "hyperparameters": {"space": [{"class_name": "Choice", "config": {"name": "activation", "default": "relu", "conditions": [], "values": ["relu", "tanh"], "ordered": false}}, {"class_name": "Int", "config": {"name": "first_units", "default": null, "conditions": [], "min_value": 1, "max_value": 100, "step": 5, "sampling": "linear"}}, {"class_name": "Int", "config": {"name": "num_layers", "default": null, "conditions": [], "min_value": 1, "max_value": 8, "step": 1, "sampling": "linear"}}, {"class_name": "Int", "config": {"name": "units_0", "default": null, "conditions": [], "min_value": 1, "max_value": 50, "step": 5, "sampling": "linear"}}, {"class_name": "Int", "config": {"name": "units_1", "default": null, "conditions": [], "min_value": 1, "max_value": 50, "step": 5, "sampling": "linear"}}, {"class_name": "Int", "config": {"name": "units_2", "default": null, "conditions": [], "min_value": 1, "max_value": 50, "step": 5, "sampling": "linear"}}, {"class_name": "Int", "config": {"name": "units_3", "default": null, "conditions": [], "min_value": 1, "max_value": 50, "step": 5, "sampling": "linear"}}, {"class_name": "Int", "config": {"name": "units_4", "default": null, "conditions": [], "min_value": 1, "max_value": 50, "step": 5, "sampling": "linear"}}, {"class_name": "Int", "config": {"name": "units_5", "default": null, "conditions": [], "min_value": 1, "max_value": 50, "step": 5, "sampling": "linear"}}, {"class_name": "Int", "config": {"name": "units_6", "default": null, "conditions": [], "min_value": 1, "max_value": 50, "step": 5, "sampling": "linear"}}, {"class_name": "Int", "config": {"name": "units_7", "default": null, "conditions": [], "min_value": 1, "max_value": 50, "step": 5, "sampling": "linear"}}], "values": {"activation": "tanh", "first_units": 46, "num_layers": 2, "units_0": 16, "units_1": 16, "units_2": 36, "units_3": 6, "units_4": 21, "units_5": 6, "units_6": 46, "units_7": 46, "tuner/epochs": 7, "tuner/initial_epoch": 3, "tuner/bracket": 3, "tuner/round": 1, "tuner/trial_id": "0121"}}, "metrics": {"metrics": {"accuracy": {"direction": "max", "observations": [{"value": [0.7313792705535889], "step": 1}]}, "loss": {"direction": "min", "observations": [{"value": [0.5503042936325073], "step": 1}]}, "val_accuracy": {"direction": "max", "observations": [{"value": [0.7306122183799744], "step": 1}]}, "val_loss": {"direction": "min", "observations": [{"value": [0.554145872592926], "step": 1}]}}}, "score": 0.7306122183799744, "best_step": 1, "status": "COMPLETED", "message": null}