{"trial_id": "0006", "hyperparameters": {"space": [{"class_name": "Choice", "config": {"name": "activation", "default": "relu", "conditions": [], "values": ["relu", "tanh"], "ordered": false}}, {"class_name": "Int", "config": {"name": "first_units", "default": null, "conditions": [], "min_value": 1, "max_value": 80, "step": 5, "sampling": "linear"}}, {"class_name": "Int", "config": {"name": "num_layers", "default": null, "conditions": [], "min_value": 1, "max_value": 5, "step": 1, "sampling": "linear"}}, {"class_name": "Int", "config": {"name": "units_0", "default": null, "conditions": [], "min_value": 1, "max_value": 40, "step": 5, "sampling": "linear"}}, {"class_name": "Int", "config": {"name": "units_1", "default": null, "conditions": [], "min_value": 1, "max_value": 40, "step": 5, "sampling": "linear"}}, {"class_name": "Int", "config": {"name": "units_2", "default": null, "conditions": [], "min_value": 1, "max_value": 40, "step": 5, "sampling": "linear"}}, {"class_name": "Int", "config": {"name": "units_3", "default": null, "conditions": [], "min_value": 1, "max_value": 40, "step": 5, "sampling": "linear"}}], "values": {"activation": "relu", "first_units": 1, "num_layers": 3, "units_0": 11, "units_1": 26, "units_2": 1, "units_3": 6, "tuner/epochs": 3, "tuner/initial_epoch": 0, "tuner/bracket": 2, "tuner/round": 0}}, "metrics": {"metrics": {"accuracy": {"direction": "max", "observations": [{"value": [0.7169180512428284], "step": 1}]}, "loss": {"direction": "min", "observations": [{"value": [0.5883336067199707], "step": 1}]}, "val_accuracy": {"direction": "max", "observations": [{"value": [0.719883382320404], "step": 1}]}, "val_loss": {"direction": "min", "observations": [{"value": [0.5810490846633911], "step": 1}]}}}, "score": 0.719883382320404, "best_step": 1, "status": "COMPLETED", "message": null}