{"trial_id": "0067", "hyperparameters": {"space": [{"class_name": "Choice", "config": {"name": "activation", "default": "relu", "conditions": [], "values": ["relu", "tanh"], "ordered": false}}, {"class_name": "Int", "config": {"name": "first_units", "default": null, "conditions": [], "min_value": 1, "max_value": 100, "step": 5, "sampling": "linear"}}, {"class_name": "Int", "config": {"name": "num_layers", "default": null, "conditions": [], "min_value": 1, "max_value": 8, "step": 1, "sampling": "linear"}}, {"class_name": "Int", "config": {"name": "units_0", "default": null, "conditions": [], "min_value": 1, "max_value": 50, "step": 5, "sampling": "linear"}}, {"class_name": "Int", "config": {"name": "units_1", "default": null, "conditions": [], "min_value": 1, "max_value": 50, "step": 5, "sampling": "linear"}}, {"class_name": "Int", "config": {"name": "units_2", "default": null, "conditions": [], "min_value": 1, "max_value": 50, "step": 5, "sampling": "linear"}}, {"class_name": "Int", "config": {"name": "units_3", "default": null, "conditions": [], "min_value": 1, "max_value": 50, "step": 5, "sampling": "linear"}}, {"class_name": "Int", "config": {"name": "units_4", "default": null, "conditions": [], "min_value": 1, "max_value": 50, "step": 5, "sampling": "linear"}}, {"class_name": "Int", "config": {"name": "units_5", "default": null, "conditions": [], "min_value": 1, "max_value": 50, "step": 5, "sampling": "linear"}}, {"class_name": "Int", "config": {"name": "units_6", "default": null, "conditions": [], "min_value": 1, "max_value": 50, "step": 5, "sampling": "linear"}}, {"class_name": "Int", "config": {"name": "units_7", "default": null, "conditions": [], "min_value": 1, "max_value": 50, "step": 5, "sampling": "linear"}}], "values": {"activation": "relu", "first_units": 66, "num_layers": 4, "units_0": 16, "units_1": 21, "units_2": 21, "units_3": 6, "units_4": 11, "units_5": 1, "units_6": 46, "units_7": 26, "tuner/epochs": 20, "tuner/initial_epoch": 7, "tuner/bracket": 2, "tuner/round": 1, "tuner/trial_id": "0061"}}, "metrics": {"metrics": {"accuracy": {"direction": "max", "observations": [{"value": [0.7339838147163391], "step": 4}]}, "loss": {"direction": "min", "observations": [{"value": [0.545455276966095], "step": 4}]}, "val_accuracy": {"direction": "max", "observations": [{"value": [0.7321282625198364], "step": 4}]}, "val_loss": {"direction": "min", "observations": [{"value": [0.5534185171127319], "step": 4}]}}}, "score": 0.7321282625198364, "best_step": 4, "status": "COMPLETED", "message": null}